setup.py
matmeta/__init__.py
matmeta/payload_metaclass.py
matmeta.egg-info/PKG-INFO
matmeta.egg-info/SOURCES.txt
matmeta.egg-info/dependency_links.txt
matmeta.egg-info/requires.txt
matmeta.egg-info/top_level.txt