Metadata-Version: 1.0
Name: matmeta
Version: 0.1.1
Summary: Common support for materials metadata
Home-page: https://github.com/MaterialsDataInfrastructureConsortium/CommonMetadata
Author: Jason Thiese
Author-email: jasonthiese@gmail.com
License: Apache v2
Platform: UNKNOWN
